torch_mutable_modules/__init__.py
torch_mutable_modules/main.py
torch_mutable_modules-1.1.2.dist-info/LICENSE
torch_mutable_modules-1.1.2.dist-info/METADATA
torch_mutable_modules-1.1.2.dist-info/WHEEL
torch_mutable_modules-1.1.2.dist-info/top_level.txt
torch_mutable_modules-1.1.2.dist-info/RECORD
