Metadata-Version: 2.1
Name: torch-mutable-modules
Version: 1.1.2
Summary: UNKNOWN
Home-page: https://github.com/KentoNishi/torch-mutable-modules
Author: KentoNishi
Author-email: kento24gs@outlook.com
License: UNKNOWN
Platform: UNKNOWN
Classifier: Programming Language :: Python :: 3
Classifier: License :: OSI Approved :: MIT License
Classifier: Operating System :: OS Independent
Requires-Python: >=3.7
Requires-Dist: torch (>=1.7.0)
